meta_cleaner/__init__.py
meta_cleaner/cleaner.py
meta_cleaner/model.py
meta_cleaner-0.4.2.dist-info/LICENSE
meta_cleaner-0.4.2.dist-info/METADATA
meta_cleaner-0.4.2.dist-info/WHEEL
meta_cleaner-0.4.2.dist-info/top_level.txt
meta_cleaner-0.4.2.dist-info/RECORD
