Metadata-Version: 2.1
Name: meta-cleaner
Version: 0.4.2
Summary: A Python package to clean text from META tags using a BERT large Longformer NER model.
Home-page: https://github.com/pirr-me/meta_cleaner
Author: Tim Isbister
Author-email: tim.isbister@pirr.me
License: UNKNOWN
Platform: UNKNOWN
Classifier: Programming Language :: Python :: 3
Classifier: License :: OSI Approved :: MIT License
Classifier: Operating System :: OS Independent
Requires-Python: >=3.10
License-File: LICENSE
Requires-Dist: torch (>=2.0.0)
Requires-Dist: transformers (>=4.0.0)
Requires-Dist: tqdm (>=4.0)
Requires-Dist: langdetect (>=1.0.8)
